pyguarantees/__init__.py
pyguarantees/constrain.py
pyguarantees/constraints.py
pyguarantees/pytests.py
pyguarantees/settings.py
pyguarantees/severity.py
pyguarantees/testcase.py
pyguarantees/unittests.py
pyguarantees/_constrain/__init__.py
pyguarantees/_constrain/_guarantee_handler.py
pyguarantees/_constraints/__init__.py
pyguarantees/_constraints/_base.py
pyguarantees/_constraints/_binary.py
pyguarantees/_constraints/_boolean.py
pyguarantees/_constraints/_class.py
pyguarantees/_constraints/_cls.py
pyguarantees/_constraints/_collections.py
pyguarantees/_constraints/_dynamic_check.py
pyguarantees/_constraints/_no_op.py
pyguarantees/_constraints/_none.py
pyguarantees/_constraints/_numeric.py
pyguarantees/_constraints/_other.py
pyguarantees/_constraints/_self.py
pyguarantees/_constraints/_string.py
pyguarantees/_constraints/_union.py
pyguarantees/_constraints/_util/__init__.py
pyguarantees/_constraints/_util/collections_checks.py
pyguarantees/_constraints/_util/common_checks.py
pyguarantees/_constraints/_util/error_handeling.py
pyguarantees/_constraints/_util/numeric_checks.py
pyguarantees/_constraints/_util/typenames.py
pyguarantees/exceptions/__init__.py
pyguarantees/exceptions/constraints.py
pyguarantees/exceptions/testcase.py
pyguarantees-0.1.4.dist-info/LICENCE.md
pyguarantees-0.1.4.dist-info/METADATA
pyguarantees-0.1.4.dist-info/WHEEL
pyguarantees-0.1.4.dist-info/top_level.txt
pyguarantees-0.1.4.dist-info/RECORD
