Metadata-Version: 2.1
Name: pyguarantees
Version: 0.1.4
Summary: guarantee testcases for callables, constrain parameters and return values of callables
Author: Sebastian Müller
Author-email: sebastian.nicolas.mueller@gmail.com
License: MIT License
Project-URL: repository, https://github.com/snimu/guarantees
Project-URL: documentation, https://github.com/snimu/guarantees#readme
Keywords: python,unittest,pytest,test,guarantees,parameters,constraints
Classifier: Programming Language :: Python
Classifier: Programming Language :: Python :: 3
Classifier: Programming Language :: Python :: 3.8
Classifier: Programming Language :: Python :: 3.9
Classifier: Programming Language :: Python :: 3.10
Classifier: Programming Language :: Python :: 3.11
Classifier: License :: OSI Approved :: MIT License
Classifier: Operating System :: OS Independent
Requires-Python: >=3.8
License-File: LICENCE.md
